flask_whooshee.py
flask_whooshee-0.9.1.dist-info/LICENSE
flask_whooshee-0.9.1.dist-info/METADATA
flask_whooshee-0.9.1.dist-info/WHEEL
flask_whooshee-0.9.1.dist-info/top_level.txt
flask_whooshee-0.9.1.dist-info/RECORD
