Metadata-Version: 2.1
Name: flask-whooshee
Version: 0.9.1
Summary: Flask-SQLAlchemy - Whoosh Integration
Home-page: https://github.com/fedora-copr/flask-whooshee
Author: Bohuslav "Slavek" Kabrda
Author-email: bkabrda@redhat.com
License: BSD-3-Clause
Keywords: flask,sqlalchemy,whoosh
Platform: any
Classifier: Development Status :: 4 - Beta
Classifier: Environment :: Web Environment
Classifier: Intended Audience :: Developers
Classifier: License :: OSI Approved :: BSD License
Classifier: Operating System :: OS Independent
Classifier: Programming Language :: Python
Classifier: Topic :: Internet :: WWW/HTTP :: Dynamic Content
Classifier: Topic :: Software Development :: Libraries :: Python Modules
License-File: LICENSE
